pydsol/core/__init__.py
pydsol/core/distributions.py
pydsol/core/eventlist.py
pydsol/core/experiment.py
pydsol/core/interfaces.py
pydsol/core/model.py
pydsol/core/parameters.py
pydsol/core/pubsub.py
pydsol/core/simevent.py
pydsol/core/simulator.py
pydsol/core/statistics.py
pydsol/core/streams.py
pydsol/core/units.py
pydsol/core/utils.py
pydsol_core-4.0.0.dist-info/LICENSE
pydsol_core-4.0.0.dist-info/METADATA
pydsol_core-4.0.0.dist-info/WHEEL
pydsol_core-4.0.0.dist-info/top_level.txt
pydsol_core-4.0.0.dist-info/RECORD
