Metadata-Version: 2.1
Name: pydsol-core
Version: 4.0.0
Summary: Python discrete-event simulation object library
Author-email: Alexander Verbraeck <a.verbraeck@gmail.com>
License: BSD 3-Clause License
Project-URL: homepage, https://simulation,tudelft.nl
Project-URL: documentation, https://pydsol-core.readthedocs.io/en/latest/
Project-URL: repository, https://github.com/averbraeck/pydsol-core
Keywords: simulation,reader,tutorial
Classifier: License :: OSI Approved :: BSD License
Classifier: Programming Language :: Python
Classifier: Programming Language :: Python :: 3
Requires-Python: >=3.9
License-File: LICENSE
Provides-Extra: dev
Requires-Dist: pytest ; extra == 'dev'
